trackerhelper/__init__.py
trackerhelper/__main__.py
trackerhelper/logging_utils.py
trackerhelper/app/__init__.py
trackerhelper/app/dedupe.py
trackerhelper/app/dedupe_reporting.py
trackerhelper/app/normalize.py
trackerhelper/app/progress.py
trackerhelper/app/release.py
trackerhelper/app/scan.py
trackerhelper/app/stats.py
trackerhelper/app/synthetic_dataset.py
trackerhelper/cli/__init__.py
trackerhelper/cli/args.py
trackerhelper/cli/common.py
trackerhelper/cli/main.py
trackerhelper/cli/progress.py
trackerhelper/cli/commands/__init__.py
trackerhelper/cli/commands/dedupe.py
trackerhelper/cli/commands/normalize.py
trackerhelper/cli/commands/release.py
trackerhelper/cli/commands/stats.py
trackerhelper/domain/__init__.py
trackerhelper/domain/constants.py
trackerhelper/domain/dedupe.py
trackerhelper/domain/grouping.py
trackerhelper/domain/models.py
trackerhelper/domain/normalize.py
trackerhelper/domain/tags.py
trackerhelper/domain/utils.py
trackerhelper/formatting/__init__.py
trackerhelper/formatting/bbcode.py
trackerhelper/formatting/bbcode_templates.py
trackerhelper/formatting/dedupe.py
trackerhelper/formatting/release.py
trackerhelper/formatting/stats.py
trackerhelper/formatting/tracklist.py
trackerhelper/infra/__init__.py
trackerhelper/infra/cover.py
trackerhelper/infra/dr.py
trackerhelper/infra/ffprobe.py
trackerhelper/infra/fingerprint.py
trackerhelper/infra/scan.py
trackerhelper-0.4.4.dist-info/licenses/LICENSE
trackerhelper-0.4.4.dist-info/METADATA
trackerhelper-0.4.4.dist-info/WHEEL
trackerhelper-0.4.4.dist-info/entry_points.txt
trackerhelper-0.4.4.dist-info/top_level.txt
trackerhelper-0.4.4.dist-info/RECORD
