Metadata-Version: 2.4
Name: trackerhelper
Version: 0.4.4
Summary: Utilities for music discography folders (stats, BBCode, normalize).
Author: pryid
License-Expression: 0BSD
Project-URL: Homepage, https://github.com/pryid/trackerhelper
Project-URL: Issues, https://github.com/pryid/trackerhelper/issues
Keywords: audio,bbcode,chromaprint,discography,ffprobe,music
Classifier: Programming Language :: Python :: 3
Classifier: Programming Language :: Python :: 3.10
Classifier: Programming Language :: Python :: 3.11
Classifier: Programming Language :: Python :: 3.12
Classifier: Operating System :: OS Independent
Requires-Python: >=3.10
License-File: LICENSE
Requires-Dist: requests
Requires-Dist: rich
Provides-Extra: dev
Requires-Dist: ruff; extra == "dev"
Requires-Dist: ty; extra == "dev"
Requires-Dist: types-requests; extra == "dev"
Dynamic: license-file
